mqtt_decorator/__init__.py
mqtt_decorator/conn.py
mqtt_decorator/route.py
mqtt_decorator-0.1.4.dist-info/LICENSE
mqtt_decorator-0.1.4.dist-info/METADATA
mqtt_decorator-0.1.4.dist-info/WHEEL
mqtt_decorator-0.1.4.dist-info/top_level.txt
mqtt_decorator-0.1.4.dist-info/RECORD
