Metadata-Version: 2.1
Name: mqtt-decorator
Version: 0.1.4
Summary: mqtt_decorator is a decorator module which  converts mqtt subscriptions and messages  to a Flask like api.
Home-page: https://github.com/mozanunal/mqtt_decorator
Author: Mehmet Ozan Unal
Author-email: mehmetozanunal@gmail.com
Maintainer: Mehmet Ozan Unal
Maintainer-email: mehmetozanunal@gmail.com
License: GPL
Platform: all
License-File: LICENSE
Requires-Dist: paho-mqtt (>=1.4.0)
